datamorph/__init__.py
datamorph/config/__init__.py
datamorph/core/__init__.py
datamorph/core/context_manager.py
datamorph/core/executor.py
datamorph/core/pipeline_loader.py
datamorph/core/runner.py
datamorph/llm/__init__.py
datamorph/llm/llm_agent.py
datamorph/llm/mock_connector.py
datamorph/llm/openai_connector.py
datamorph/llm/prompts.py
datamorph/steps/__init__.py
datamorph/steps/dynamo_writer.py
datamorph/steps/registry.py
datamorph/steps/s3_loader.py
datamorph/steps/summarize.py
datamorph/steps/transform.py
datamorph/ui/__init__.py
datamorph/ui/app.py
datamorph/ui/pipeline_utils.py
datamorph/utils/__init__.py
datamorph/utils/error_handler.py
datamorph/utils/file_ops.py
datamorph/utils/logger.py
datamorph/utils/timer.py
pydatamorph-1.1.7.dist-info/licenses/LICENSE
pydatamorph-1.1.7.dist-info/METADATA
pydatamorph-1.1.7.dist-info/WHEEL
pydatamorph-1.1.7.dist-info/entry_points.txt
pydatamorph-1.1.7.dist-info/top_level.txt
pydatamorph-1.1.7.dist-info/RECORD
